svgpipe/__init__.py
svgpipe/inject.py
svgpipe/tests/__init__.py
svgpipe/tests/test_inject.py
svgpipe-0.2.0.dist-info/LICENSE
svgpipe-0.2.0.dist-info/METADATA
svgpipe-0.2.0.dist-info/WHEEL
svgpipe-0.2.0.dist-info/top_level.txt
svgpipe-0.2.0.dist-info/RECORD
