Metadata-Version: 2.1
Name: svgpipe
Version: 0.2.0
Summary: Transactions on existing SVG documents: inject/extract/modify
Home-page: https://github.com/broesamle/svgpipe
Author: Martin Brösamle
Author-email: m@martinbroesamle.de
License: UNKNOWN
Keywords: svg,vector graphics,scalable vector graphics,xml,visualisation
Platform: UNKNOWN
Classifier: Programming Language :: Python :: 3
Classifier: License :: OSI Approved :: MIT License
Classifier: Operating System :: OS Independent
Classifier: Topic :: Multimedia :: Graphics
Classifier: Topic :: Scientific/Engineering :: Visualization
Classifier: Intended Audience :: Science/Research
Requires-Python: >=3.7
